nomad_camels_driver_voltcraft_psp/voltcraft_psp.py
nomad_camels_driver_voltcraft_psp/voltcraft_psp_ophyd.py
nomad_camels_driver_voltcraft_psp-0.1.1.dist-info/licenses/LICENSE.txt
nomad_camels_driver_voltcraft_psp-0.1.1.dist-info/METADATA
nomad_camels_driver_voltcraft_psp-0.1.1.dist-info/WHEEL
nomad_camels_driver_voltcraft_psp-0.1.1.dist-info/top_level.txt
nomad_camels_driver_voltcraft_psp-0.1.1.dist-info/RECORD
